listmatch/__init__.py
listmatch/listmatch.py
listmatch/util.py
listmatch-0.2.0.dist-info/DESCRIPTION.rst
listmatch-0.2.0.dist-info/METADATA
listmatch-0.2.0.dist-info/RECORD
listmatch-0.2.0.dist-info/WHEEL
listmatch-0.2.0.dist-info/metadata.json
listmatch-0.2.0.dist-info/top_level.txt
