Metadata-Version: 2.0
Name: listmatch
Version: 0.2.0
Summary: Regexes for lists.
Home-page: https://github.com/pokey/listmatch
Author: Pokey Rule
Author-email: pokey.rule@gmail.com
License: MIT license
Keywords: listmatch
Platform: UNKNOWN
Classifier: Development Status :: 2 - Pre-Alpha
Classifier: Intended Audience :: Developers
Classifier: License :: OSI Approved :: MIT License
Classifier: Natural Language :: English
Classifier: Programming Language :: Python :: 2
Classifier: Programming Language :: Python :: 2.6
Classifier: Programming Language :: Python :: 2.7
Classifier: Programming Language :: Python :: 3
Classifier: Programming Language :: Python :: 3.3
Classifier: Programming Language :: Python :: 3.4
Classifier: Programming Language :: Python :: 3.5
